Metadata-Version: 2.1
Name: scope
Version: 0.3.2
Summary: Metrics logging and analysis
Home-page: http://github.com/danijar/scope
Classifier: Intended Audience :: Science/Research
Classifier: License :: OSI Approved :: MIT License
Classifier: Programming Language :: Python :: 3
License-File: LICENSE
